py3_logger/__init__.py
py3_logger/logger.py
py3_logger/rotating_file_handler.py
py3_logger-0.0.7.dist-info/METADATA
py3_logger-0.0.7.dist-info/WHEEL
py3_logger-0.0.7.dist-info/licenses/LICENSE
py3_logger-0.0.7.dist-info/RECORD
